smgen/__init__.py
smgen/app.py
smgen/generator.py
smgen/parser.py
smgen/writer.py
smgen/templates/__init__.py
smgen/templates/context.py
smgen/templates/ctx_transition.py
smgen/templates/import.py
smgen/templates/state.py
smgen/templates/state_enum.py
smgen/templates/state_tmpl.py
smgen/templates/transition_none.py
smgen/templates/transition_ok.py
smgen-0.0.4.dist-info/LICENSE.md
smgen-0.0.4.dist-info/METADATA
smgen-0.0.4.dist-info/WHEEL
smgen-0.0.4.dist-info/top_level.txt
smgen-0.0.4.dist-info/RECORD
