Metadata-Version: 2.1
Name: smgen
Version: 0.0.4
Summary: Code generator to create state machine
Home-page: https://github.com/hellstein/statemachine
Author: phoenix.lv
Author-email: phoenix.grey0108@gmail.com
License: UNKNOWN
Platform: UNKNOWN
Classifier: Programming Language :: Python :: 3
Classifier: License :: OSI Approved :: MIT License
Classifier: Operating System :: OS Independent
